xzxTool/HandleCsv.py
xzxTool/__init__.py
xzxTool/op.py
xzxTool-2024.10.10.dist-info/LICENSE
xzxTool-2024.10.10.dist-info/METADATA
xzxTool-2024.10.10.dist-info/WHEEL
xzxTool-2024.10.10.dist-info/top_level.txt
xzxTool-2024.10.10.dist-info/RECORD
